GSKhopt/Experiment.py
GSKhopt/Logger.py
GSKhopt/Models.py
GSKhopt/SolutionMapper.py
GSKhopt/__init__.py
GSKhopt/config.py
GSKhopt/linear_reg.py
GSKhopt/run.py
GSKhopt/utils.py
GSKhopt/CSVDataFrame/CSVDataFrame.py
GSKhopt/CSVDataFrame/LittleFrame.py
GSKhopt/CSVDataFrame/Vectorize.py
GSKhopt/CSVDataFrame/__init__.py
GSKhopt/CSVDataFrame/main.py
GSKhopt/CSVDataFrame/utils_numbers.py
GSKhopt/GSKpy/AGSK.py
GSKhopt/GSKpy/BasicGSK.py
GSKhopt/GSKpy/GSK.py
GSKhopt/GSKpy/GSKHpot.py
GSKhopt/GSKpy/GSKLSPR.py
GSKhopt/GSKpy/Gained_Shared_Junior_R1R2R3.py
GSKhopt/GSKpy/Gained_Shared_Middle_R1R2R3.py
GSKhopt/GSKpy/Gained_Shared_Senior_R1R2R3.py
GSKhopt/GSKpy/__init__.py
GSKhopt/GSKpy/boundConstraint.py
GSKhopt/GSKpy/viz.py
GSKhopt/Objectives/DNN.py
GSKhopt/Objectives/KerasCNN.py
GSKhopt/Objectives/__init__.py
GSKhopt/Objectives/eval.py
GSKhopt-0.0.6.dist-info/METADATA
GSKhopt-0.0.6.dist-info/WHEEL
GSKhopt-0.0.6.dist-info/top_level.txt
GSKhopt-0.0.6.dist-info/RECORD
