Metadata-Version: 2.1
Name: GSKhopt
Version: 0.0.6
Summary: GSK algorithm for efficient hyperparameter optimization
Home-page: https://github.com/ha2emnomer/GSKHpot/
Author: Hazem Nomer
Author-email: h.nomer@nu.edu.eg
License: UNKNOWN
Project-URL: Bug Tracker, https://github.com/ha2emnomer/GSKHpot/issues
Platform: UNKNOWN
Classifier: Programming Language :: Python :: 3
Classifier: License :: OSI Approved :: MIT License
Classifier: Operating System :: OS Independent
Requires-Python: >=3.6
